libdots/__init__.py
libdots/io/__init__.py
libdots/io/input_data_inventory.py
libdots/io/io_data.py
libdots/io/message_definitions/healthcheck.proto
libdots/io/message_definitions/lifecycle.proto
libdots/io/messages/__init__.py
libdots/io/messages/healthcheck_pb2.py
libdots/io/messages/healthcheck_pb2.pyi
libdots/io/messages/lifecycle_pb2.py
libdots/io/messages/lifecycle_pb2.pyi
libdots/io/mqtt_client.py
libdots/io/mqtt_log_handler.py
libdots/model/__init__.py
libdots/model/config.py
libdots/model/esdl_parser.py
libdots/model/influxdb_connector.py
libdots/model/service.py
libdots/model/service_calc.py
libdots/profiles.py
libdots/py.typed
libdots/types.py
libdots-1.6.4.dist-info/LICENSE.txt
libdots-1.6.4.dist-info/METADATA
libdots-1.6.4.dist-info/WHEEL
libdots-1.6.4.dist-info/RECORD
